MANIFEST.in
README.rst
setup.py
metzoo/__init__.py
metzoo/lib/__init__.py
metzoo/lib/agent.py
metzoo/lib/config.py
metzoo/lib/db.py
metzoo/lib/errors.py
metzoo/lib/functions.py
metzoo/lib/utils.py
metzoo_python_lib.egg-info/PKG-INFO
metzoo_python_lib.egg-info/SOURCES.txt
metzoo_python_lib.egg-info/dependency_links.txt
metzoo_python_lib.egg-info/not-zip-safe
metzoo_python_lib.egg-info/requires.txt
metzoo_python_lib.egg-info/top_level.txt