Metadata-Version: 1.1
Name: metzoo-python-lib
Version: 0.0.16
Summary: Python Database Library for Metzoo
Home-page: https://bitbucket.org/edrans/metzoo-python-lib
Author: Edrans
Author-email: info@edrans.com
License: MIT
Keywords: metzoo monitoring metric
Platform: UNKNOWN
Classifier: Development Status :: 4 - Beta
Classifier: License :: OSI Approved :: MIT License
Classifier: Programming Language :: Python :: 2.7
